cost_monitoring_construct/__init__.py
cost_monitoring_construct/py.typed
cost_monitoring_construct/_jsii/__init__.py
cost_monitoring_construct/_jsii/cost-monitoring-construct@1.2.3.jsii.tgz
cost_monitoring_construct-1.2.3.dist-info/LICENSE
cost_monitoring_construct-1.2.3.dist-info/METADATA
cost_monitoring_construct-1.2.3.dist-info/WHEEL
cost_monitoring_construct-1.2.3.dist-info/top_level.txt
cost_monitoring_construct-1.2.3.dist-info/RECORD
